paper_jsoneditor/__init__.py
paper_jsoneditor/fields.py
paper_jsoneditor/forms.py
paper_jsoneditor/widgets.py
paper_jsoneditor/static/paper_jsoneditor/dist/widget.css
paper_jsoneditor/static/paper_jsoneditor/dist/widget.js
paper_jsoneditor/static/paper_jsoneditor/dist/widget.js.LICENSE.txt
paper_jsoneditor/static/paper_jsoneditor/dist/widget.js.map
paper_jsoneditor/static/paper_jsoneditor/dist/assets/jsoneditor-icons.svg
paper_jsoneditor/templates/paper_jsoneditor/widget.html
paper_jsoneditor-0.4.1.dist-info/LICENSE
paper_jsoneditor-0.4.1.dist-info/METADATA
paper_jsoneditor-0.4.1.dist-info/WHEEL
paper_jsoneditor-0.4.1.dist-info/top_level.txt
paper_jsoneditor-0.4.1.dist-info/RECORD
